{
    "eval_eng_Latn_loss": 7.1782026290893555,
    "eval_eng_Latn_runtime": 3.1594,
    "eval_eng_Latn_samples_per_second": 320.319,
    "eval_eng_Latn_steps_per_second": 40.198,
    "epoch": 3.0,
    "eval_spa_Latn_loss": 5.8869194984436035,
    "eval_spa_Latn_runtime": 3.1432,
    "eval_spa_Latn_samples_per_second": 321.962,
    "eval_spa_Latn_steps_per_second": 40.404,
    "eval_ita_Latn_loss": 7.267913818359375,
    "eval_ita_Latn_runtime": 3.1094,
    "eval_ita_Latn_samples_per_second": 325.464,
    "eval_ita_Latn_steps_per_second": 40.844,
    "eval_deu_Latn_loss": 6.535266399383545,
    "eval_deu_Latn_runtime": 3.1784,
    "eval_deu_Latn_samples_per_second": 318.403,
    "eval_deu_Latn_steps_per_second": 39.958,
    "eval_arb_Arab_loss": 6.583502292633057,
    "eval_arb_Arab_runtime": 3.1933,
    "eval_arb_Arab_samples_per_second": 316.916,
    "eval_arb_Arab_steps_per_second": 39.771,
    "eval_tel_Telu_loss": 6.185192584991455,
    "eval_tel_Telu_runtime": 3.171,
    "eval_tel_Telu_samples_per_second": 319.147,
    "eval_tel_Telu_steps_per_second": 40.051,
    "eval_tam_Taml_loss": 6.038182258605957,
    "eval_tam_Taml_runtime": 3.1472,
    "eval_tam_Taml_samples_per_second": 321.551,
    "eval_tam_Taml_steps_per_second": 40.353,
    "eval_quy_Latn_loss": 7.283454895019531,
    "eval_quy_Latn_runtime": 3.1893,
    "eval_quy_Latn_samples_per_second": 317.313,
    "eval_quy_Latn_steps_per_second": 39.821,
    "eval_zho_Hans_loss": 6.577286720275879,
    "eval_zho_Hans_runtime": 3.1744,
    "eval_zho_Hans_samples_per_second": 318.796,
    "eval_zho_Hans_steps_per_second": 40.007
}